{
    "HEADER_TITLE": "ZIONN",
    "MENU_ITEM_DOCUMENTS": "ДОКУМЕНТИ КОМПАНІЇ",
    "MENU_ITEM_LICENSE": "ЛІЦЕНЗІЯ",
    "MENU_ITEM_INSURANCE": "СТРАХУВАННЯ",
    "MENU_ITEM_CONTACT": "КОНТАКТИ",
    "INFO_TEXT": "Транспортна компанія Zionn - ваш надійний партнер для перевезення вантажів вагою до 3,5 тонн. Знаходячись у Кракові, ми спеціалізуємося на ефективних, швидких та безпечних перевезеннях по всій Європі. Наша компанія має ліцензію на надання послуг з перевезень та пропонує страхування вантажів, забезпечуючи повний захист вашому вантажу. Завдяки нашій команді професійних водіїв і досвідченій логістиці ми пишаємося наданням послуг високої якості, які відповідають потребам наших клієнтів. Незалежно від того, чи потрібно вам перевезти вантаж об'ємом до 1 тонни, чи інші нетипові вантажи, ми забезпечуємо повне відстеження вантажу в режимі реального часу. Ми готові запропонувати оптимальний варіант для вашого логістичного завдання.З Zionn ви можете бути впевнені в надійності та професіоналізмі кожної вантажної перевезення.",
    "CONTACT_TITLE": "Контакти:",
    "CONTACT_PHONE": "Тел: +48690056215",
    "CONTACT_FAX": "Факс: +48690056215",
    "CONTACT_EMAIL": "Електронна пошта: zionn@onet.pl",
    "ADDRESS_HOURS": "Години роботи\nПонеділок - П'ятниця\n09.00 - 17.00",
    "ADDRESS_LOCATION": "Адреса: Zionn вул. Шлях 77/222, 31-153 Краків"
}